pytcolor/__init__.py
pytcolor/colors.py
pytcolor/constants.py
tests/__init__.py
tests/test_apply_color.py
pytcolor-1.0.0.1.dist-info/LICENSE
pytcolor-1.0.0.1.dist-info/METADATA
pytcolor-1.0.0.1.dist-info/WHEEL
pytcolor-1.0.0.1.dist-info/top_level.txt
pytcolor-1.0.0.1.dist-info/RECORD
