Metadata-Version: 2.1
Name: pytcolor
Version: 1.0.0.1
Summary: Python Terminal Color
Home-page: https://github.com/midhuncnair/PyTcolor
Author: Midhun C Nair
Author-email: midhunch@gmail.com
License: MIT LICENSE
Keywords: pycolor,pytermcolor,python-color,python-terminal-color,terminal-color,color-logging,py-color-logging,python-color-logging
Platform: UNKNOWN
Classifier: Programming Language :: Python :: 3
Classifier: License :: OSI Approved :: MIT License
Classifier: Operating System :: OS Independent
Requires-Python: >=3.0.0
